datetime_tzutils.py
datetime_tzutils-1.0.1.dist-info/LICENSE
datetime_tzutils-1.0.1.dist-info/WHEEL
datetime_tzutils-1.0.1.dist-info/METADATA
datetime_tzutils-1.0.1.dist-info/RECORD
