Metadata-Version: 2.1
Name: datetime_tzutils
Version: 1.0.1
Summary: datetime.datetime helper functions for converting to/from UTC and other datetime manipulations
Author-email: Rhet Turnbull <rturnbull+git@gmail.com>
Classifier: License :: OSI Approved :: MIT License
Project-URL: Home, https://github.com/RhetTbull/datetime_tzutils
